high_templar/__init__.py
high_templar/connection.py
high_templar/hub.py
high_templar/main.py
high_templar/room.py
high_templar/test.py
high_templar-2.4.2.dist-info/LICENSE
high_templar-2.4.2.dist-info/METADATA
high_templar-2.4.2.dist-info/WHEEL
high_templar-2.4.2.dist-info/top_level.txt
high_templar-2.4.2.dist-info/RECORD
