Metadata-Version: 2.1
Name: high-templar
Version: 2.4.2
Summary: A python framework for creating a server which handles websockets for an existing API
Home-page: https://github.com/CodeYellowBV/high-templar
Author: Code Yellow B.V.
Author-email: pypi@codeyellow.nl
License: MIT
Platform: UNKNOWN
Classifier: Development Status :: 3 - Alpha
Classifier: Environment :: Web Environment
Classifier: Intended Audience :: Developers
Classifier: License :: OSI Approved :: MIT License
Classifier: Operating System :: OS Independent
Classifier: Programming Language :: Python :: 3
Classifier: Programming Language :: Python :: 3.3
Classifier: Programming Language :: Python :: 3.4
Classifier: Programming Language :: Python :: 3.5
Classifier: Programming Language :: Python :: 3.6
Classifier: Topic :: Internet :: WWW/HTTP :: Dynamic Content
Classifier: Topic :: Software Development :: Libraries :: Python Modules
Requires-Dist: gevent (<1.4.0,>=1.1.2)
Requires-Dist: greenlet (>=0.4.12)
Requires-Dist: Flask (>=0.12.0)
Requires-Dist: Flask-Sockets (>=0.2.1)
Requires-Dist: python-dotenv (>=0.6.3)
Requires-Dist: requests (>=2.13.0)
